LICENSE
MANIFEST.in
README.rst
setup.py
pysolver.egg-info/PKG-INFO
pysolver.egg-info/SOURCES.txt
pysolver.egg-info/dependency_links.txt
pysolver.egg-info/requires.txt
pysolver.egg-info/top_level.txt
solver/__init__.py
solver/base.py
solver/celeryconf.py
solver/expts.py
solver/tasks.py
solver/tests.py