Metadata-Version: 1.1
Name: pysolver
Version: 0.0.1
Summary: Make a problem solution process easier
Home-page: https://github.com/scidam/solver
Author: Dmitry E. Kislov
Author-email: kislov@easydan.com
License: UNKNOWN
Keywords: Python solver,problem solver,task templates,solution templates engine,computational problems,mathematics
Platform: UNKNOWN
Classifier: Development Status :: 2 - Pre-Alpha
Classifier: Environment :: Other Environment
Classifier: Intended Audience :: Developers
Classifier: Intended Audience :: Education
Classifier: Intended Audience :: Science/Research
Classifier: License :: OSI Approved :: MIT License
Classifier: Operating System :: OS Independent
Classifier: Programming Language :: Python
Classifier: Programming Language :: Python :: 3
Classifier: Topic :: Education
Classifier: Topic :: Scientific/Engineering
Classifier: Topic :: Scientific/Engineering :: Mathematics
